{"BaseModel.2c320ed0-69b6-4a1f-b8ef-000f42ce25bb": {"id": "2c320ed0-69b6-4a1f-b8ef-000f42ce25bb", "created_at": "2023-05-14T10:58:28.709858", "updated_at": "2023-05-14T10:58:28.709878", "name": "My_First_Model", "my_number": 89, "__class__": "BaseModel"}, "BaseModel.00e034cc-9efd-4cde-92e3-7b34ab34c6a4": {"id": "00e034cc-9efd-4cde-92e3-7b34ab34c6a4", "created_at": "2023-05-14T10:59:58.313131", "updated_at": "2023-05-14T10:59:58.313141", "name": "My_First_Model", "my_number": 89, "__class__": "BaseModel"}, "BaseModel.e5e04e2d-ac78-43c5-843d-093c6922ff46": {"id": "e5e04e2d-ac78-43c5-843d-093c6922ff46", "created_at": "2023-05-14T11:09:26.105242", "updated_at": "2023-05-14T11:09:26.105496", "name": "My First Model", "my_number": 89, "__class__": "BaseModel"}, "User.ffb8d2e6-1cf3-4d8c-80de-9ecb8b2cbef4": {"id": "ffb8d2e6-1cf3-4d8c-80de-9ecb8b2cbef4", "created_at": "2023-05-14T11:13:50.606061", "updated_at": "2023-05-14T11:13:50.606073", "first_name": "Chimsale", "email": "airbnb2@mail.com", "password": "root", "name": "Khumbize", "age": 21, "__class__": "User"}, "State.23fc58fd-d626-4b8e-99ef-826f64d91874": {"name": "California", "id": "23fc58fd-d626-4b8e-99ef-826f64d91874", "created_at": "2023-06-21T11:15:31.250407", "updated_at": "2023-06-21T11:15:31.250423", "__class__": "State"}, "State.8f21fd5c-3402-48dd-9750-89756566dc6a": {"name": "Arizona", "id": "8f21fd5c-3402-48dd-9750-89756566dc6a", "created_at": "2023-06-21T11:15:31.344870", "updated_at": "2023-06-21T11:15:31.344883", "__class__": "State"}, "Place.f8789148-7b47-4f90-a5ad-7c72b202784d": {"city_id": "0001", "user_id": "0001", "name": "My little house", "number_rooms": 4, "number_bathrooms": 2, "max_guest": 10, "price_by_night": 300, "latitude": 37.773972, "longitude": -122.431297, "id": "f8789148-7b47-4f90-a5ad-7c72b202784d", "created_at": "2023-06-21T11:15:31.346178", "updated_at": "2023-06-21T11:15:31.346192", "__class__": "Place"}, "State.6da27744-7b3b-40ce-a845-8d7a4806a867": {"name": "California", "id": "6da27744-7b3b-40ce-a845-8d7a4806a867", "created_at": "2023-06-21T11:22:46.043826", "updated_at": "2023-06-21T11:22:46.043835", "__class__": "State"}, "State.c8e05a60-4423-4f32-8fce-1eef572d00e8": {"name": "Arizona", "id": "c8e05a60-4423-4f32-8fce-1eef572d00e8", "created_at": "2023-06-21T11:22:46.044304", "updated_at": "2023-06-21T11:22:46.044314", "__class__": "State"}, "Place.4319a775-df87-4c0a-a4a1-ddc5b67f07d6": {"city_id": "0001", "user_id": "0001", "name": "My little house", "number_rooms": 4, "number_bathrooms": 2, "max_guest": 10, "price_by_night": 300, "latitude": 37.773972, "longitude": -122.431297, "id": "4319a775-df87-4c0a-a4a1-ddc5b67f07d6", "created_at": "2023-06-21T11:22:46.046076", "updated_at": "2023-06-21T11:22:46.046089", "__class__": "Place"}, "State.cd0f7c99-32a7-4755-bc27-2106d6f11e19": {"id": "cd0f7c99-32a7-4755-bc27-2106d6f11e19", "created_at": "2023-06-21T11:41:32.841906", "updated_at": "2023-06-21T11:41:32.841906", "name": "California", "__class__": "State"}, "State.1c4fa28d-1af6-4539-972a-308bede9e06f": {"id": "1c4fa28d-1af6-4539-972a-308bede9e06f", "created_at": "2023-06-21T11:41:32.843305", "updated_at": "2023-06-21T11:41:32.843305", "name": "Nevada", "__class__": "State"}}